README.md
setup.py
pt/__init__.py
pt/cmd.py
pt/cmd_options.py
pt/apps/chat/chat.py
pt/apps/chat/templates/index.html
pt/apps/gcp/gcp.py
pt/apps/server/ubuntu.py
pt/apps/ws/btc.py
pt/apps/ws/btc_straddle.py
pt/apps/ws/main.py
pt/apps/ws/okex.py
pt/apps/ws/test.py
pt/libs/cloudflare.py
pt/libs/ndb_model.py
pt/libs/pt_email.py
pt/libs/utils.py
pt/libs/block_chain/eth.py
pt/libs/flask_httpauth/flask_httpauth.py
pt/libs/flask_jwt/__init__.py
pt/libs/payment/paypal.py
pt_py.egg-info/PKG-INFO
pt_py.egg-info/SOURCES.txt
pt_py.egg-info/dependency_links.txt
pt_py.egg-info/entry_points.txt
pt_py.egg-info/not-zip-safe
pt_py.egg-info/requires.txt
pt_py.egg-info/top_level.txt